LICENSE
MANIFEST.in
README.md
setup.py
django_mix_admin/__init__.py
django_mix_admin/decorators.py
django_mix_admin/forms.py
django_mix_admin/models.py
django_mix_admin/options.py
django_mix_admin/sites.py
django_mix_admin/utils.py
django_mix_admin/views.py
django_mix_admin/widgets.py
django_mix_admin.egg-info/PKG-INFO
django_mix_admin.egg-info/SOURCES.txt
django_mix_admin.egg-info/dependency_links.txt
django_mix_admin.egg-info/requires.txt
django_mix_admin.egg-info/top_level.txt
django_mix_admin/helpers/__init__.py
django_mix_admin/helpers/xlsx_exporter.py
django_mix_admin/helpers/xlsx_importer.py
django_mix_admin/static/admin/css/xbase.css
django_mix_admin/static/admin/ele_date_picker/EleDatePicker.css
django_mix_admin/static/admin/ele_date_picker/EleDatePicker.umd.min.js
django_mix_admin/static/admin/ele_date_picker/ele_date_picker.js
django_mix_admin/static/admin/ele_date_picker/fonts/element-icons.535877f5.woff
django_mix_admin/static/admin/ele_date_picker/fonts/element-icons.732389de.ttf
django_mix_admin/static/admin/img/down.png
django_mix_admin/static/admin/img/file.jpg
django_mix_admin/static/admin/img/next.png
django_mix_admin/static/admin/img/player1.jpg
django_mix_admin/static/admin/js/binding_wx.js
django_mix_admin/static/admin/js/custom_action_0222.js
django_mix_admin/static/admin/js/file_agent_0119.js
django_mix_admin/static/admin/js/jquery.init.js
django_mix_admin/static/admin/js/mix_admin_02041.js
django_mix_admin/static/admin/js/preview_files_0113.js
django_mix_admin/static/admin/js/sidebar.js
django_mix_admin/templates/admin/actions.html
django_mix_admin/templates/admin/base.html
django_mix_admin/templates/admin/change_list.html
django_mix_admin/templates/admin/change_list_object_tools.html
django_mix_admin/templates/admin/filter.html
django_mix_admin/templates/admin/search_form.html
django_mix_admin/templates/admin/sidebar.html
django_mix_admin/templates/admin/submit_line.html
django_mix_admin/templates/admin/edit_inline/tabular.html
django_mix_admin/templates/admin/widgets/mix_input_option.html
django_mix_admin/templates/admin/widgets/mix_radio.html
django_mix_admin/templates/admin/widgets/related_widget_wrapper.html
